revproxy_auth/__init__.py
revproxy_auth/config-template.yml
revproxy_auth/revproxy_auth.py
revproxy_auth/revproxy_auth_static/__init__.py
revproxy_auth/revproxy_auth_static/css/__init__.py
revproxy_auth/revproxy_auth_static/css/view.css
revproxy_auth/templates/__init__.py
revproxy_auth/templates/form.html
tests/__init__.py
tests/test_000.py
tests/test_001.py
tests/data/__init__.py
revproxy_auth-0.1.16.dist-info/METADATA
revproxy_auth-0.1.16.dist-info/WHEEL
revproxy_auth-0.1.16.dist-info/top_level.txt
revproxy_auth-0.1.16.dist-info/RECORD
