Metadata-Version: 2.1
Name: revproxy-auth
Version: 0.1.16
Summary: Reverse proxy with synology authentication
Home-page: https://github.com/Phornee/revproxy_auth
Author: Ismael Raya
Author-email: phornee@gmail.com
Classifier: Programming Language :: Python :: 3
Classifier: License :: OSI Approved :: MIT License
Classifier: Operating System :: OS Independent
Classifier: Topic :: Home Automation
Requires-Python: >=3.11
Requires-Dist: Flask>=3.1.0
Requires-Dist: config-yml>=0.3.0
Requires-Dist: beautifulsoup4>=4.13.3
Requires-Dist: requests>=2.32.3
